Metadata-Version: 2.1
Name: calculateAG
Version: 1.0
Summary: A basic calculator module
Author: Artūras Grygelis
Author-email: arturas.grygelis@gmail.com
Keywords: python,calculator,mathematics
Classifier: Development Status :: 3 - Alpha
Classifier: Programming Language :: Python :: 3
Classifier: Programming Language :: Python :: 3.6
Classifier: Programming Language :: Python :: 3.7
Classifier: Programming Language :: Python :: 3.8
Classifier: Programming Language :: Python :: 3.9
Classifier: Operating System :: Unix
Classifier: Operating System :: MacOS :: MacOS X
Classifier: Operating System :: Microsoft :: Windows
License-File: LICENSE.txt
